odoo/addons/product_template_tags/README.rst
odoo/addons/product_template_tags/__init__.py
odoo/addons/product_template_tags/__manifest__.py
odoo/addons/product_template_tags/i18n/de.po
odoo/addons/product_template_tags/i18n/es.po
odoo/addons/product_template_tags/i18n/fr.po
odoo/addons/product_template_tags/i18n/hr.po
odoo/addons/product_template_tags/i18n/it.po
odoo/addons/product_template_tags/i18n/nl_NL.po
odoo/addons/product_template_tags/i18n/product_template_tags.pot
odoo/addons/product_template_tags/i18n/sl.po
odoo/addons/product_template_tags/models/__init__.py
odoo/addons/product_template_tags/models/product_template.py
odoo/addons/product_template_tags/models/product_template_tag.py
odoo/addons/product_template_tags/security/product_template_rule.xml
odoo/addons/product_template_tags/security/product_template_tag.xml
odoo/addons/product_template_tags/static/description/icon.png
odoo/addons/product_template_tags/views/product_template.xml
odoo/addons/product_template_tags/views/product_template_tag.xml
odoo11_addon_product_template_tags-11.0.1.0.0.99.dev10.dist-info/METADATA
odoo11_addon_product_template_tags-11.0.1.0.0.99.dev10.dist-info/WHEEL
odoo11_addon_product_template_tags-11.0.1.0.0.99.dev10.dist-info/top_level.txt
odoo11_addon_product_template_tags-11.0.1.0.0.99.dev10.dist-info/RECORD
